{
    "pbt-1": [
        { "name": "Наличие воды", "value": 100, "time": "2025-03-12T12:30" },
        { "name": "Объем", "value": 500, "time": "2025-03-12T12:35" },
        { "name": "Плотность", "value": 50, "time": "2025-03-12T12:30" },
        { "name": "Наличие воды", "value": 84, "time": "2025-03-12T13:50" },
        { "name": "Объем", "value": 437, "time": "2025-03-12T15:20" },
        { "name": "Плотность", "value": 60, "time": "2025-03-12T15:20" }
    ],
    "pbt-2": [
        { "name": "Наличие воды", "value": 800, "time": "2025-03-12T12:30" },
        { "name": "Объем", "value": 250, "time": "2025-03-12T13:15" },
        { "name": "Плотность", "value": 26, "time": "2025-03-12T12:30" },
        { "name": "Наличие воды", "value": 679, "time": "2025-03-12T13:49" },
        { "name": "Объем", "value": 298, "time": "2025-03-12T15:19" },
        { "name": "Плотность", "value": 13, "time": "2025-03-12T15:20" }
    ],
    "pbt-3": [
        { "name": "Наличие воды", "value": 800, "time": "2025-03-12T12:30" },
        { "name": "Объем", "value": 250, "time": "2025-03-12T13:15" },
        { "name": "Плотность", "value": 90, "time": "2025-03-12T12:30" },
        { "name": "Наличие воды", "value": 679, "time": "2025-03-12T13:49" },
        { "name": "Объем", "value": 298, "time": "2025-03-12T15:19" },
        { "name": "Плотность", "value": 99, "time": "2025-03-12T15:20" }
    ],
    "pbt-4": [
        { "name": "Наличие воды", "value": 100, "time": "2025-03-12T12:30" },
        { "name": "Объем", "value": 500, "time": "2025-03-12T12:35" },
        { "name": "Плотность", "value": 50, "time": "2025-03-12T12:30" },
        { "name": "Наличие воды", "value": 84, "time": "2025-03-12T13:50" },
        { "name": "Объем", "value": 437, "time": "2025-03-12T15:20" },
        { "name": "Плотность", "value": 60, "time": "2025-03-12T15:20" }
    ],
    "ydh-1": [
        { "name": "Наличие воды", "value": 800, "time": "2025-03-12T12:30" },
        { "name": "Объем", "value": 250, "time": "2025-03-12T13:15" },
        { "name": "Плотность", "value": 26, "time": "2025-03-12T12:30" },
        { "name": "Наличие воды", "value": 679, "time": "2025-03-12T13:49" },
        { "name": "Объем", "value": 298, "time": "2025-03-12T15:19" },
        { "name": "Плотность", "value": 13, "time": "2025-03-12T15:20" }
    ],
    "ydh-2": [
        { "name": "Наличие воды", "value": 800, "time": "2025-03-12T12:30" },
        { "name": "Объем", "value": 250, "time": "2025-03-12T13:15" },
        { "name": "Плотность", "value": 26, "time": "2025-03-12T12:30" },
        { "name": "Наличие воды", "value": 679, "time": "2025-03-12T13:49" },
        { "name": "Объем", "value": 298, "time": "2025-03-12T15:19" },
        { "name": "Плотность", "value": 13, "time": "2025-03-12T15:20" }
    ],
    "bdr": [
        { "name": "Наличие воды", "value": 800, "time": "2025-03-12T12:30" },
        { "name": "Объем", "value": 250, "time": "2025-03-12T13:15" },
        { "name": "Плотность", "value": 26, "time": "2025-03-12T12:30" },
        { "name": "Наличие воды", "value": 679, "time": "2025-03-12T13:49" },
        { "name": "Объем", "value": 298, "time": "2025-03-12T15:19" },
        { "name": "Плотность", "value": 13, "time": "2025-03-12T15:20" }
    ],
    "gs-1": [
        { "name": "Наличие воды", "value": 800, "time": "2025-03-12T12:30" },
        { "name": "Объем", "value": 250, "time": "2025-03-12T13:15" },
        { "name": "Плотность", "value": 90, "time": "2025-03-12T12:30" },
        { "name": "Наличие воды", "value": 679, "time": "2025-03-12T13:49" },
        { "name": "Объем", "value": 298, "time": "2025-03-12T15:19" },
        { "name": "Плотность", "value": 99, "time": "2025-03-12T15:20" }
    ],
    "gs-2": [
        { "name": "Наличие воды", "value": 100, "time": "2025-03-12T12:30" },
        { "name": "Объем", "value": 500, "time": "2025-03-12T12:35" },
        { "name": "Плотность", "value": 50, "time": "2025-03-12T12:30" },
        { "name": "Наличие воды", "value": 84, "time": "2025-03-12T13:50" },
        { "name": "Объем", "value": 437, "time": "2025-03-12T15:20" },
        { "name": "Плотность", "value": 60, "time": "2025-03-12T15:20" }
    ],
    "s-1_1": [
        { "name": "Наличие воды", "value": 800, "time": "2025-03-12T12:30" },
        { "name": "Объем", "value": 250, "time": "2025-03-12T13:15" },
        { "name": "Плотность", "value": 26, "time": "2025-03-12T12:30" },
        { "name": "Наличие воды", "value": 679, "time": "2025-03-12T13:49" },
        { "name": "Объем", "value": 298, "time": "2025-03-12T15:19" },
        { "name": "Плотность", "value": 13, "time": "2025-03-12T15:20" }
    ],
    "s-1_2": [
        { "name": "Наличие воды", "value": 800, "time": "2025-03-12T12:30" },
        { "name": "Объем", "value": 250, "time": "2025-03-12T13:15" },
        { "name": "Плотность", "value": 90, "time": "2025-03-12T12:30" },
        { "name": "Наличие воды", "value": 679, "time": "2025-03-12T13:49" },
        { "name": "Объем", "value": 298, "time": "2025-03-12T15:19" },
        { "name": "Плотность", "value": 99, "time": "2025-03-12T15:20" }
    ],
    "s-2_1": [
        { "name": "Наличие воды", "value": 100, "time": "2025-03-12T12:30" },
        { "name": "Объем", "value": 500, "time": "2025-03-12T12:35" },
        { "name": "Плотность", "value": 50, "time": "2025-03-12T12:30" },
        { "name": "Наличие воды", "value": 84, "time": "2025-03-12T13:50" },
        { "name": "Объем", "value": 437, "time": "2025-03-12T15:20" },
        { "name": "Плотность", "value": 60, "time": "2025-03-12T15:20" }
    ],
    "s-2_2": [
        { "name": "Наличие воды", "value": 800, "time": "2025-03-12T12:30" },
        { "name": "Объем", "value": 250, "time": "2025-03-12T13:15" },
        { "name": "Плотность", "value": 26, "time": "2025-03-12T12:30" },
        { "name": "Наличие воды", "value": 679, "time": "2025-03-12T13:49" },
        { "name": "Объем", "value": 298, "time": "2025-03-12T15:19" },
        { "name": "Плотность", "value": 13, "time": "2025-03-12T15:20" }
    ],
    "ksy-1": [
        { "name": "Наличие воды", "value": 800, "time": "2025-03-12T12:30" },
        { "name": "Объем", "value": 250, "time": "2025-03-12T13:15" },
        { "name": "Плотность", "value": 90, "time": "2025-03-12T12:30" },
        { "name": "Наличие воды", "value": 679, "time": "2025-03-12T13:49" },
        { "name": "Объем", "value": 298, "time": "2025-03-12T15:19" },
        { "name": "Плотность", "value": 99, "time": "2025-03-12T15:20" }
    ],
    "ksy-2": [
        { "name": "Наличие воды", "value": 100, "time": "2025-03-12T12:30" },
        { "name": "Объем", "value": 500, "time": "2025-03-12T12:35" },
        { "name": "Плотность", "value": 50, "time": "2025-03-12T12:30" },
        { "name": "Наличие воды", "value": 84, "time": "2025-03-12T13:50" },
        { "name": "Объем", "value": 437, "time": "2025-03-12T15:20" },
        { "name": "Плотность", "value": 60, "time": "2025-03-12T15:20" }
    ],
    "rvs-1": [
        { "name": "Наличие воды", "value": 800, "time": "2025-03-12T12:30" },
        { "name": "Объем", "value": 250, "time": "2025-03-12T13:15" },
        { "name": "Плотность", "value": 26, "time": "2025-03-12T12:30" },
        { "name": "Наличие воды", "value": 679, "time": "2025-03-12T13:49" },
        { "name": "Объем", "value": 298, "time": "2025-03-12T15:19" },
        { "name": "Плотность", "value": 13, "time": "2025-03-12T15:20" }
    ],
    "rvs-2": [
        { "name": "Наличие воды", "value": 800, "time": "2025-03-12T12:30" },
        { "name": "Объем", "value": 250, "time": "2025-03-12T13:15" },
        { "name": "Плотность", "value": 90, "time": "2025-03-12T12:30" },
        { "name": "Наличие воды", "value": 679, "time": "2025-03-12T13:49" },
        { "name": "Объем", "value": 298, "time": "2025-03-12T15:19" },
        { "name": "Плотность", "value": 99, "time": "2025-03-12T15:20" }
    ],
    "rvs-3": [
        { "name": "Наличие воды", "value": 100, "time": "2025-03-12T12:30" },
        { "name": "Объем", "value": 500, "time": "2025-03-12T12:35" },
        { "name": "Плотность", "value": 50, "time": "2025-03-12T12:30" },
        { "name": "Наличие воды", "value": 84, "time": "2025-03-12T13:50" },
        { "name": "Объем", "value": 437, "time": "2025-03-12T15:20" },
        { "name": "Плотность", "value": 60, "time": "2025-03-12T15:20" }
    ],
    "rvs-4": [
        { "name": "Наличие воды", "value": 800, "time": "2025-03-12T12:30" },
        { "name": "Объем", "value": 250, "time": "2025-03-12T13:15" },
        { "name": "Плотность", "value": 26, "time": "2025-03-12T12:30" },
        { "name": "Наличие воды", "value": 679, "time": "2025-03-12T13:49" },
        { "name": "Объем", "value": 298, "time": "2025-03-12T15:19" },
        { "name": "Плотность", "value": 13, "time": "2025-03-12T15:20" }
    ],
    "rvs-5": [
        { "name": "Наличие воды", "value": 800, "time": "2025-03-12T12:30" },
        { "name": "Объем", "value": 250, "time": "2025-03-12T13:15" },
        { "name": "Плотность", "value": 90, "time": "2025-03-12T12:30" },
        { "name": "Наличие воды", "value": 679, "time": "2025-03-12T13:49" },
        { "name": "Объем", "value": 298, "time": "2025-03-12T15:19" },
        { "name": "Плотность", "value": 99, "time": "2025-03-12T15:20" }
    ],
    "rvs-6": [
        { "name": "Наличие воды", "value": 800, "time": "2025-03-12T12:30" },
        { "name": "Объем", "value": 250, "time": "2025-03-12T13:15" },
        { "name": "Плотность", "value": 90, "time": "2025-03-12T12:30" },
        { "name": "Наличие воды", "value": 679, "time": "2025-03-12T13:49" },
        { "name": "Объем", "value": 298, "time": "2025-03-12T15:19" },
        { "name": "Плотность", "value": 99, "time": "2025-03-12T15:20" }
    ],
    "t1": [
        { "name": "Наличие воды", "value": 800, "time": "2025-03-12T12:30" },
        { "name": "Объем", "value": 250, "time": "2025-03-12T13:15" },
        { "name": "Плотность", "value": 90, "time": "2025-03-12T12:30" },
        { "name": "Наличие воды", "value": 679, "time": "2025-03-12T13:49" },
        { "name": "Объем", "value": 298, "time": "2025-03-12T15:19" },
        { "name": "Плотность", "value": 99, "time": "2025-03-12T15:20" }
    ],
    "t2": [
        { "name": "Наличие воды", "value": 800, "time": "2025-03-12T12:30" },
        { "name": "Объем", "value": 250, "time": "2025-03-12T13:15" },
        { "name": "Плотность", "value": 90, "time": "2025-03-12T12:30" },
        { "name": "Наличие воды", "value": 679, "time": "2025-03-12T13:49" },
        { "name": "Объем", "value": 298, "time": "2025-03-12T15:19" },
        { "name": "Плотность", "value": 99, "time": "2025-03-12T15:20" }
    ],
    "t3": [
        { "name": "Наличие воды", "value": 800, "time": "2025-03-12T12:30" },
        { "name": "Объем", "value": 250, "time": "2025-03-12T13:15" },
        { "name": "Плотность", "value": 90, "time": "2025-03-12T12:30" },
        { "name": "Наличие воды", "value": 679, "time": "2025-03-12T13:49" },
        { "name": "Объем", "value": 298, "time": "2025-03-12T15:19" },
        { "name": "Плотность", "value": 99, "time": "2025-03-12T15:20" }
    ],
    "ov-1": [
        { "name": "Наличие воды", "value": 800, "time": "2025-03-12T12:30" },
        { "name": "Объем", "value": 250, "time": "2025-03-12T13:15" },
        { "name": "Плотность", "value": 90, "time": "2025-03-12T12:30" },
        { "name": "Наличие воды", "value": 679, "time": "2025-03-12T13:49" },
        { "name": "Объем", "value": 298, "time": "2025-03-12T15:19" },
        { "name": "Плотность", "value": 99, "time": "2025-03-12T15:20" }
    ],
    "ov-2": [
        { "name": "Наличие воды", "value": 800, "time": "2025-03-12T12:30" },
        { "name": "Объем", "value": 250, "time": "2025-03-12T13:15" },
        { "name": "Плотность", "value": 90, "time": "2025-03-12T12:30" },
        { "name": "Наличие воды", "value": 679, "time": "2025-03-12T13:49" },
        { "name": "Объем", "value": 298, "time": "2025-03-12T15:19" },
        { "name": "Плотность", "value": 99, "time": "2025-03-12T15:20" }
    ],
    "ynra": [
        { "name": "Наличие воды", "value": 800, "time": "2025-03-12T12:30" },
        { "name": "Объем", "value": 250, "time": "2025-03-12T13:15" },
        { "name": "Плотность", "value": 90, "time": "2025-03-12T12:30" },
        { "name": "Наличие воды", "value": 679, "time": "2025-03-12T13:49" },
        { "name": "Объем", "value": 298, "time": "2025-03-12T15:19" },
        { "name": "Плотность", "value": 99, "time": "2025-03-12T15:20" }
    ],
    "ypog": [
        { "name": "Наличие воды", "value": 800, "time": "2025-03-12T12:30" },
        { "name": "Объем", "value": 250, "time": "2025-03-12T13:15" },
        { "name": "Плотность", "value": 90, "time": "2025-03-12T12:30" },
        { "name": "Наличие воды", "value": 679, "time": "2025-03-12T13:49" },
        { "name": "Объем", "value": 298, "time": "2025-03-12T15:19" },
        { "name": "Плотность", "value": 99, "time": "2025-03-12T15:20" }
    ],
    "bnks": [
        { "name": "Наличие воды", "value": 800, "time": "2025-03-12T12:30" },
        { "name": "Объем", "value": 250, "time": "2025-03-12T13:15" },
        { "name": "Плотность", "value": 90, "time": "2025-03-12T12:30" },
        { "name": "Наличие воды", "value": 679, "time": "2025-03-12T13:49" },
        { "name": "Объем", "value": 298, "time": "2025-03-12T15:19" },
        { "name": "Плотность", "value": 99, "time": "2025-03-12T15:20" }
    ],
    "in-greb": [
        { "name": "Наличие воды", "value": 800, "time": "2025-03-12T12:30" },
        { "name": "Объем", "value": 250, "time": "2025-03-12T13:15" },
        { "name": "Плотность", "value": 90, "time": "2025-03-12T12:30" },
        { "name": "Наличие воды", "value": 679, "time": "2025-03-12T13:49" },
        { "name": "Объем", "value": 298, "time": "2025-03-12T15:19" },
        { "name": "Плотность", "value": 99, "time": "2025-03-12T15:20" }
    ],
    "bir": [
        { "name": "Наличие воды", "value": 800, "time": "2025-03-12T12:30" },
        { "name": "Объем", "value": 250, "time": "2025-03-12T13:15" },
        { "name": "Плотность", "value": 90, "time": "2025-03-12T12:30" },
        { "name": "Наличие воды", "value": 679, "time": "2025-03-12T13:49" },
        { "name": "Объем", "value": 298, "time": "2025-03-12T15:19" },
        { "name": "Плотность", "value": 99, "time": "2025-03-12T15:20" }
    ],
    "sikn-1": [
        { "name": "Наличие воды", "value": 800, "time": "2025-03-12T12:30" },
        { "name": "Объем", "value": 250, "time": "2025-03-12T13:15" },
        { "name": "Плотность", "value": 90, "time": "2025-03-12T12:30" },
        { "name": "Наличие воды", "value": 679, "time": "2025-03-12T13:49" },
        { "name": "Объем", "value": 298, "time": "2025-03-12T15:19" },
        { "name": "Плотность", "value": 99, "time": "2025-03-12T15:20" }
    ],
    "pump-1": [
        { "name": "Наличие воды", "value": 800, "time": "2025-03-12T12:30" },
        { "name": "Объем", "value": 250, "time": "2025-03-12T13:15" },
        { "name": "Плотность", "value": 90, "time": "2025-03-12T12:30" },
        { "name": "Наличие воды", "value": 679, "time": "2025-03-12T13:49" },
        { "name": "Объем", "value": 298, "time": "2025-03-12T15:19" },
        { "name": "Плотность", "value": 99, "time": "2025-03-12T15:20" }
    ],
    "tube-1": [
        { "name": "Наличие воды", "value": 800, "time": "2025-03-12T12:30" },
        { "name": "Объем", "value": 250, "time": "2025-03-12T13:15" },
        { "name": "Плотность", "value": 90, "time": "2025-03-12T12:30" },
        { "name": "Наличие воды", "value": 679, "time": "2025-03-12T13:49" },
        { "name": "Объем", "value": 298, "time": "2025-03-12T15:19" },
        { "name": "Плотность", "value": 99, "time": "2025-03-12T15:20" }
    ]
}